{
	"miniprogramRoot": "dist/",
	"projectname": "blog-minApp-1",
	"description": "",
	"appid": "wx768fdb55a82f87fe",
	"setting": {
		"urlCheck": true,
		"es6": false,
		"postcss": false,
		"minified": false,
		"newFeature": true,
		"coverView": true,
		"autoAudits": false,
		"showShadowRootInWxmlPanel": false,
		"scopeDataCheck": false,
		"checkInvalidKey": true,
		"checkSiteMap": true,
		"uploadWithSourceMap": true,
		"babelSetting": {
			"ignore": [],
			"disablePlugins": [],
			"outputPath": ""
		}
	},
	"compileType": "miniprogram",
	"simulatorType": "wechat",
	"simulatorPluginLibVersion": {},
	"scripts": {
		"beforeCompile": "npm run tsc",
		"beforePreview": "npm run tsc",
		"beforeUpload": "npm run tsc"
	},
	"condition": {
		"search": {
			"current": -1,
			"list": []
		},
		"conversation": {
			"current": -1,
			"list": []
		},
		"plugin": {
			"current": -1,
			"list": []
		},
		"game": {
			"list": []
		},
		"gamePlugin": {
			"current": -1,
			"list": []
		},
		"miniprogram": {
			"current": -1,
			"list": [
				{
					"id": 0,
					"name": "Project",
					"pathName": "pages/Project/Project",
					"scene": null
				},
				{
					"id": 1,
					"name": "Article",
					"pathName": "pages/Article/Article",
					"scene": null
				},
				{
					"id": -1,
					"name": "home",
					"pathName": "pages/Home/Home",
					"scene": null
				}
			]
		}
	}
}